{"transcript":"Υà…în…êΥ¨viΥÄs…ê","exists":true,"definitions":["En person der underviser andre, typisk i en skole eller pΟΞ et universitet.","En person der formidler viden eller fΟΠrdigheder til en gruppe elever eller studerende."],"examples":["Underviseren forklarede den komplekse teori.","Alle undervisere deltog i mΟΗdet.","Hun er en erfaren underviser."],"lemma":"undervise","lemmaPos":"verb","synonyms":["lΟΠrer","instruktΟΗr","pΟΠdagog"],"number":"singular","pluralForm":"undervisere","gender":"common","source":"underviser"}